<?xml version="1.0" encoding="utf-8" ?>
<Quotes>
<Quote>
<Author>Greg Rucka</Author>
<Language>English</Language>
<QuoteValue>I'm a Caucasian American Jew. These are all things that make up who I am</QuoteValue>
</Quote>
<Quote>
<Author>Greg Rucka</Author>
<Language>English</Language>
<QuoteValue>Character is made up of a variety of different things. One of those elements is gender</QuoteValue>
</Quote>
<Quote>
<Author>Greg Rucka</Author>
<Language>English</Language>
<QuoteValue>My college senior thesis was going to be on the American private investigator</QuoteValue>
</Quote>
<Quote>
<Author>Greg Rutherford</Author>
<Language>English</Language>
<QuoteValue>I do a lot of things like running hills and larger amounts of reps in the gym</QuoteValue>
</Quote>
<Quote>
<Author>Greg Rutherford</Author>
<Language>English</Language>
<QuoteValue>It's all about proving it on the track and proving to people that have different views wrong</QuoteValue>
</Quote>
<Quote>
<Author>Greg Rutherford</Author>
<Language>English</Language>
<QuoteValue>To put up with me, you have to be patient</QuoteValue>
</Quote>
<Quote>
<Author>Greg Rutherford</Author>
<Language>English</Language>
<QuoteValue>I've not received any major sponsorship deals or anything else</QuoteValue>
</Quote>
<Quote>
<Author>Greg Rutherford</Author>
<Language>English</Language>
<QuoteValue>Over the years, I've had torrid luck with things going wrong</QuoteValue>
</Quote>
<Quote>
<Author>Greg Rutherford</Author>
<Language>English</Language>
<QuoteValue>I'm excited by going 85 mph, head-first, down an ice track</QuoteValue>
</Quote>
<Quote>
<Author>Greg Rutherford</Author>
<Language>English</Language>
<QuoteValue>I'm never happy to settle</QuoteValue>
</Quote>
<Quote>
<Author>Greg Rutherford</Author>
<Language>English</Language>
<QuoteValue>Ultimately, I love the sport; I love doing what I do</QuoteValue>
</Quote>
<Quote>
<Author>Greg Rutherford</Author>
<Language>English</Language>
<QuoteValue>I was always the slightly fat kid, which used to bother me quite a bit</QuoteValue>
</Quote>
<Quote>
<Author>Greg Rutherford</Author>
<Language>English</Language>
<QuoteValue>My dad is a builder, and my mum's a nurse. They're just very normal people</QuoteValue>
</Quote>
<Quote>
<Author>Gregg Allman</Author>
<Language>English</Language>
<QuoteValue>I play every show like it's my last. Fortunately, that's never turned out to be the case</QuoteValue>
</Quote>
<Quote>
<Author>Gregg Allman</Author>
<Language>English</Language>
<QuoteValue>Gotta take my puppy on the road with me, Killer</QuoteValue>
</Quote>
<Quote>
<Author>Gregg Allman</Author>
<Language>English</Language>
<QuoteValue>I didn't think we would ever make enough money to pay rent by playing music</QuoteValue>
</Quote>
<Quote>
<Author>Gregg Allman</Author>
<Language>English</Language>
<QuoteValue>I got Jimmy Hall from Wet Willie and he also plays now with Hank Williams Jr</QuoteValue>
</Quote>
<Quote>
<Author>Gregg Allman</Author>
<Language>English</Language>
<QuoteValue>I have been going to the gym instead of the bar, trying to get back down to my fighting weight</QuoteValue>
</Quote>
<Quote>
<Author>Gregg Allman</Author>
<Language>English</Language>
<QuoteValue>The Beatles had just come out, and everybody had a band. It was incredible competition out there</QuoteValue>
</Quote>
<Quote>
<Author>Gregg Allman</Author>
<Language>English</Language>
<QuoteValue>There are as many ways to write songs as there are songs</QuoteValue>
</Quote>
<Quote>
<Author>Gregg Allman</Author>
<Language>English</Language>
<QuoteValue>I've come to the conclusion that I'm not supposed to be married</QuoteValue>
</Quote>
<Quote>
<Author>Gregg Allman</Author>
<Language>English</Language>
<QuoteValue>Before I got into rock n' roll, I was going to be a dentist</QuoteValue>
</Quote>
<Quote>
<Author>Gregg Allman</Author>
<Language>English</Language>
<QuoteValue>Duane Allman was the best guitar player I ever heard who didn't read a note</QuoteValue>
</Quote>
<Quote>
<Author>Gregory Bateson</Author>
<Language>English</Language>
<QuoteValue>Science, like art, religion, commerce, warfare, and even sleep, is based on presuppositions</QuoteValue>
</Quote>
<Quote>
<Author>Gregory Bateson</Author>
<Language>English</Language>
<QuoteValue>Language commonly stresses only one side of any interaction</QuoteValue>
</Quote>
<Quote>
<Author>Gregory Bateson</Author>
<Language>English</Language>
<QuoteValue>All experience is subjective</QuoteValue>
</Quote>
<Quote>
<Author>Gregory Bateson</Author>
<Language>English</Language>
<QuoteValue>Money is always transitively valued. More money is supposedly always better than less money</QuoteValue>
</Quote>
<Quote>
<Author>Gregory Bateson</Author>
<Language>English</Language>
<QuoteValue>It is impossible, in principle, to explain any pattern by invoking a single quantity</QuoteValue>
</Quote>
<Quote>
<Author>Gregory Bateson</Author>
<Language>English</Language>
<QuoteValue>Logic is a poor model of cause and effect</QuoteValue>
</Quote>
<Quote>
<Author>Gregory Bateson</Author>
<Language>English</Language>
<QuoteValue>We do not know enough about how the present will lead into the future</QuoteValue>
</Quote>
<Quote>
<Author>Gregory Bateson</Author>
<Language>English</Language>
<QuoteValue>Every move we make in fear of the next war in fact hastens it</QuoteValue>
</Quote>
<Quote>
<Author>Gregory Bateson</Author>
<Language>English</Language>
<QuoteValue>Logic can often be reversed, but the effect does not precede the cause</QuoteValue>
</Quote>
<Quote>
<Author>Gregory Bateson</Author>
<Language>English</Language>
<QuoteValue>Number is different from quantity</QuoteValue>
</Quote>
<Quote>
<Author>Greta Garbo</Author>
<Language>English</Language>
<QuoteValue>If you are blessed, you are blessed, whether you are married or single</QuoteValue>
</Quote>
<Quote>
<Author>Greta Garbo</Author>
<Language>English</Language>
<QuoteValue>I wish I were supernaturally strong so I could put right everything that is wrong</QuoteValue>
</Quote>
<Quote>
<Author>Greta Garbo</Author>
<Language>English</Language>
<QuoteValue>Is there anything better than to be longing for something, when you know it is within reach?</QuoteValue>
</Quote>
<Quote>
<Author>Greta Garbo</Author>
<Language>English</Language>
<QuoteValue>If only those who dream about Hollywood knew how difficult it all is</QuoteValue>
</Quote>
<Quote>
<Author>Greta Garbo</Author>
<Language>English</Language>
<QuoteValue>There is no one who would have me - I can't cook</QuoteValue>
</Quote>
<Quote>
<Author>Greta Garbo</Author>
<Language>English</Language>
<QuoteValue>Life would be so wonderful if we only knew what to do with it</QuoteValue>
</Quote>
<Quote>
<Author>Greta Garbo</Author>
<Language>English</Language>
<QuoteValue>My talents fall within definite limitations. I am not as versatile an actress as some think</QuoteValue>
</Quote>
<Quote>
<Author>Greta Garbo</Author>
<Language>English</Language>
<QuoteValue>Anyone who has a continuous smile on his face conceals a toughness that is almost frightening</QuoteValue>
</Quote>
<Quote>
<Author>Greta Garbo</Author>
<Language>English</Language>
<QuoteValue>This is where I have wasted the best years of my life</QuoteValue>
</Quote>
<Quote>
<Author>Greta Garbo</Author>
<Language>English</Language>
<QuoteValue>I want to be alone</QuoteValue>
</Quote>
<Quote>
<Author>Gretchen Rubin</Author>
<Language>English</Language>
<QuoteValue>If you've had something for more than six months, and it's still not repaired, it's clutter</QuoteValue>
</Quote>
<Quote>
<Author>Gretchen Rubin</Author>
<Language>English</Language>
<QuoteValue>One of my most important 'Secrets of Adulthood': Outer order contributes to inner calm</QuoteValue>
</Quote>
<Quote>
<Author>Gretchen Rubin</Author>
<Language>English</Language>
<QuoteValue>Getting paperwork under control makes me feel more in control of my life generally</QuoteValue>
</Quote>
<Quote>
<Author>Gretchen Rubin</Author>
<Language>English</Language>
<QuoteValue>Children's literature is one of my joys, and it's also my mental comfort food</QuoteValue>
</Quote>
<Quote>
<Author>Gretchen Rubin</Author>
<Language>English</Language>
<QuoteValue>Accept yourself and expect more from yourself</QuoteValue>
</Quote>
<Quote>
<Author>Gretchen Rubin</Author>
<Language>English</Language>
<QuoteValue>Working is one of the most dangerous forms of procrastination</QuoteValue>
</Quote>
<Quote>
<Author>Gretchen Rubin</Author>
<Language>English</Language>
<QuoteValue>I always feel calmer when I exercise. In fact, that's probably the main reason I exercise</QuoteValue>
</Quote>
<Quote>
<Author>Gretchen Rubin</Author>
<Language>English</Language>
<QuoteValue>I get such a buzz out of cleaning closets</QuoteValue>
</Quote>
<Quote>
<Author>Gretchen Rubin</Author>
<Language>English</Language>
<QuoteValue>I'm much calmer when there's no TV or music playing in the background</QuoteValue>
</Quote>
<Quote>
<Author>Gretchen Rubin</Author>
<Language>English</Language>
<QuoteValue>In 'Happier at Home,' I write a lot about my struggle to create an unhurried atmosphere at home</QuoteValue>
</Quote>
<Quote>
<Author>Grimes</Author>
<Language>English</Language>
<QuoteValue>The most valuable live thing for me is when people look like they're having a good time</QuoteValue>
</Quote>
<Quote>
<Author>Grimes</Author>
<Language>English</Language>
<QuoteValue>If I'm a bad mood, I can't go on stage and smile</QuoteValue>
</Quote>
<Quote>
<Author>Grimes</Author>
<Language>English</Language>
<QuoteValue>I'm a very nervous, shy person</QuoteValue>
</Quote>
<Quote>
<Author>Grimes</Author>
<Language>English</Language>
<QuoteValue>I'm against spending money to record</QuoteValue>
</Quote>
<Quote>
<Author>Grimes</Author>
<Language>English</Language>
<QuoteValue>I can't censor myself; it's really important for me to say how I feel</QuoteValue>
</Quote>
<Quote>
<Author>Grimes</Author>
<Language>English</Language>
<QuoteValue>I was incredibly unpopular in high school but also extremely notorious</QuoteValue>
</Quote>
<Quote>
<Author>Grimes</Author>
<Language>English</Language>
<QuoteValue>I'm not, like, a natural performer. It's sort of a thing that I've had to learn to do</QuoteValue>
</Quote>
<Quote>
<Author>Grimes</Author>
<Language>English</Language>
<QuoteValue>Especially with music, people want confidence</QuoteValue>
</Quote>
<Quote>
<Author>Grimes</Author>
<Language>English</Language>
<QuoteValue>Success, for me, is a song that can deliver shivers</QuoteValue>
</Quote>
<Quote>
<Author>Grimes</Author>
<Language>English</Language>
<QuoteValue>Basically, I'm really impressionable and have no sense of consistency in anything I do</QuoteValue>
</Quote>
<Quote>
<Author>Grover Norquist</Author>
<Language>English</Language>
<QuoteValue>Hypocrisy is the tribute that vice pays to virtue</QuoteValue>
</Quote>
<Quote>
<Author>Grover Norquist</Author>
<Language>English</Language>
<QuoteValue>Our goal is to shrink government to the size where we can drown it in a bathtub</QuoteValue>
</Quote>
<Quote>
<Author>Grover Norquist</Author>
<Language>English</Language>
<QuoteValue>The tax issue is the most powerful issue in American politics going back to the Tea Party</QuoteValue>
</Quote>
<Quote>
<Author>Grover Norquist</Author>
<Language>English</Language>
<QuoteValue>Compromise is moving in the right directlon more slowly than one might like</QuoteValue>
</Quote>
<Quote>
<Author>Grover Norquist</Author>
<Language>English</Language>
<QuoteValue>Obsessions turn people off</QuoteValue>
</Quote>
<Quote>
<Author>Grover Norquist</Author>
<Language>English</Language>
<QuoteValue>Being married is kind of like being a Ken-doll; you don't get to dress yourself anymore</QuoteValue>
</Quote>
<Quote>
<Author>Grover Norquist</Author>
<Language>English</Language>
<QuoteValue>The statists want to control the economy</QuoteValue>
</Quote>
<Quote>
<Author>Grover Norquist</Author>
<Language>English</Language>
<QuoteValue>My ideal citizen is the self-employed, homeschooling, IRA-owning guy with a concealed-carry permit</QuoteValue>
</Quote>
<Quote>
<Author>Grover Norquist</Author>
<Language>English</Language>
<QuoteValue>When I was younger, I thought of myself as a Nixon Republican because he was the anti-Communist</QuoteValue>
</Quote>
<Quote>
<Author>Grover Norquist</Author>
<Language>English</Language>
<QuoteValue>Not continuing a tax cut is not technically a tax increase</QuoteValue>
</Quote>
<Quote>
<Author>Gugu Mbath</Author>
<Language>English</Language>
<QuoteValue>aw - I'm interested in playing lots of different complex women</QuoteValue>
</Quote>
<Quote>
<Author>Gugu Mbath</Author>
<Language>English</Language>
<QuoteValue>aw - You have to be able to appreciate who you are</QuoteValue>
</Quote>
<Quote>
<Author>Gugu Mbath</Author>
<Language>English</Language>
<QuoteValue>aw - Speaking as a mixed-race woman, there aren't many historical stories about people like me</QuoteValue>
</Quote>
<Quote>
<Author>Gugu Mbath</Author>
<Language>English</Language>
<QuoteValue>aw - When I was nine, 'The Borrowers' was such a big series for me!</QuoteValue>
</Quote>
<Quote>
<Author>Gugu Mbath</Author>
<Language>English</Language>
<QuoteValue>aw - I think there are parts of myself in every character I play</QuoteValue>
</Quote>
<Quote>
<Author>Gugu Mbath</Author>
<Language>English</Language>
<QuoteValue>aw - I try not to define myself. Other people are going to do that for you anyway</QuoteValue>
</Quote>
<Quote>
<Author>Gugu Mbath</Author>
<Language>English</Language>
<QuoteValue>aw - I played Dorothy in 'The Wizard of Oz.' That was my first role on stage</QuoteValue>
</Quote>
<Quote>
<Author>Gugu Mbath</Author>
<Language>English</Language>
<QuoteValue>aw - In 2009, I was living in London and getting work I enjoyed</QuoteValue>
</Quote>
<Quote>
<Author>Gugu Mbath</Author>
<Language>English</Language>
<QuoteValue>aw - I feel like I learn in every project</QuoteValue>
</Quote>
<Quote>
<Author>Gugu Mbath</Author>
<Language>English</Language>
<QuoteValue>aw - I feel like my work has been incredibly diverse</QuoteValue>
</Quote>
<Quote>
<Author>Guru Nanak</Author>
<Language>English</Language>
<QuoteValue>Let no man in the world live in delusion. Without a Guru none can cross over to the other shore</QuoteValue>
</Quote>
<Quote>
<Author>Guru Nanak</Author>
<Language>English</Language>
<QuoteValue>Through shallow intellect, the mind becomes shallow, and one eats the fly, along with the sweets</QuoteValue>
</Quote>
<Quote>
<Author>Guru Nanak</Author>
<Language>English</Language>
<QuoteValue>Riches cannot be gathered without sin and evil means</QuoteValue>
</Quote>
<Quote>
<Author>Guru Nanak</Author>
<Language>English</Language>
<QuoteValue>I am neither a child, a young man, nor an ancient; nor am I of any caste</QuoteValue>
</Quote>
<Quote>
<Author>Guru Nanak</Author>
<Language>English</Language>
<QuoteValue>I bow at His Feet constantly, and pray to Him, the Guru, the True Guru, has shown me the Way</QuoteValue>
</Quote>
<Quote>
<Author>Guru Nanak</Author>
<Language>English</Language>
<QuoteValue>One cannot comprehend Him through reason, even if one reasoned for ages</QuoteValue>
</Quote>
<Quote>
<Author>Guru Nanak</Author>
<Language>English</Language>
<QuoteValue>I am not the born; how can there be either birth or death for me?</QuoteValue>
</Quote>
<Quote>
<Author>Guru Nanak</Author>
<Language>English</Language>
<QuoteValue>From its brilliancy everything is illuminated</QuoteValue>
</Quote>
<Quote>
<Author>Guru Nanak</Author>
<Language>English</Language>
<QuoteValue>Thou has a thousand eyes and yet not one eye; Thou host a thousand forms and yet not one form</QuoteValue>
</Quote>
<Quote>
<Author>Guru Nanak</Author>
<Language>English</Language>
<QuoteValue>Let God's grace be the mosque, and devotion the prayer mat. Let the Quran be the good conduct</QuoteValue>
</Quote>
<Quote>
<Author>Gus Van Sant</Author>
<Language>English</Language>
<QuoteValue>Free time keeps me going</QuoteValue>
</Quote>
<Quote>
<Author>Gus Van Sant</Author>
<Language>English</Language>
<QuoteValue>I was once a shameless, full-time dope fiend</QuoteValue>
</Quote>
<Quote>
<Author>Gus Van Sant</Author>
<Language>English</Language>
<QuoteValue>For all the boredom the straight life brings, it's not too bad</QuoteValue>
</Quote>
<Quote>
<Author>Gus Van Sant</Author>
<Language>English</Language>
<QuoteValue>I mean, I think I'm pretty sentimental</QuoteValue>
</Quote>
<Quote>
<Author>Gus Van Sant</Author>
<Language>English</Language>
<QuoteValue>There's always a risk if you don't do things the way you've done things before</QuoteValue>
</Quote>
<Quote>
<Author>Gus Van Sant</Author>
<Language>English</Language>
<QuoteValue>I'm normally drawn to something I haven't done and seen before</QuoteValue>
</Quote>
<Quote>
<Author>Gus Van Sant</Author>
<Language>English</Language>
<QuoteValue>Usually people just hire me</QuoteValue>
</Quote>
<Quote>
<Author>Gus Van Sant</Author>
<Language>English</Language>
<QuoteValue>When you get to be 23, 24 or 25, you start to freeze up and become an adult</QuoteValue>
</Quote>
<Quote>
<Author>Gus Van Sant</Author>
<Language>English</Language>
<QuoteValue>Sometimes, the people who are helping you can drop the ball</QuoteValue>
</Quote>
<Quote>
<Author>Gus Van Sant</Author>
<Language>English</Language>
<QuoteValue>Everything's changing so fast that it's sometimes hard to keep up</QuoteValue>
</Quote>
<Quote>
<Author>Gustav Mahler</Author>
<Language>English</Language>
<QuoteValue>A symphony must be like the world. It must contain everything</QuoteValue>
</Quote>
<Quote>
<Author>Gustav Mahler</Author>
<Language>English</Language>
<QuoteValue>I am hitting my head against the walls, but the walls are giving way</QuoteValue>
</Quote>
<Quote>
<Author>Gustav Mahler</Author>
<Language>English</Language>
<QuoteValue>It should be one's sole endeavor to see everything afresh and create it anew</QuoteValue>
</Quote>
<Quote>
<Author>Gustav Mahler</Author>
<Language>English</Language>
<QuoteValue>Fortunately, something always remains to be harvested. So let us not be idle</QuoteValue>
</Quote>
<Quote>
<Author>Gustav Mahler</Author>
<Language>English</Language>
<QuoteValue>I don't let myself get carried away by my own ideas - I abandon 19 out of 20 of them every day</QuoteValue>
</Quote>
<Quote>
<Author>Gustav Mahler</Author>
<Language>English</Language>
<QuoteValue>Don't bother looking at the view - I have already composed it</QuoteValue>
</Quote>
<Quote>
<Author>Gustav Mahler</Author>
<Language>English</Language>
<QuoteValue>If you think you're boring your audience, go slower not faster</QuoteValue>
</Quote>
<Quote>
<Author>Gustav Mahler</Author>
<Language>English</Language>
<QuoteValue>It is strange how one feels drawn forward without knowing at first where one is going</QuoteValue>
</Quote>
<Quote>
<Author>Gustav Mahler</Author>
<Language>English</Language>
<QuoteValue>If a composer could say what he had to say in words he would not bother trying to say it in music</QuoteValue>
</Quote>
<Quote>
<Author>Gustav Mahler</Author>
<Language>English</Language>
<QuoteValue>I hope you will no longer accuse me of a lack of delicacy. as I now count on your understanding</QuoteValue>
</Quote>
<Quote>
<Author>Gustave Flaubert</Author>
<Language>English</Language>
<QuoteValue>The art of writing is the art of discovering what you believe</QuoteValue>
</Quote>
<Quote>
<Author>Gustave Flaubert</Author>
<Language>English</Language>
<QuoteValue>There is no truth. There is only perception</QuoteValue>
</Quote>
<Quote>
<Author>Gustave Flaubert</Author>
<Language>English</Language>
<QuoteValue>Success is a consequence and must not be a goal</QuoteValue>
</Quote>
<Quote>
<Author>Gustave Flaubert</Author>
<Language>English</Language>
<QuoteValue>Nothing is more humiliating than to see idiots succeed in enterprises we have failed in</QuoteValue>
</Quote>
<Quote>
<Author>Gustave Flaubert</Author>
<Language>English</Language>
<QuoteValue>I believe that if one always looked at the skies, one would end up with wings</QuoteValue>
</Quote>
<Quote>
<Author>Gustave Flaubert</Author>
<Language>English</Language>
<QuoteValue>Exuberance is better than taste</QuoteValue>
</Quote>
<Quote>
<Author>Gustave Flaubert</Author>
<Language>English</Language>
<QuoteValue>Artists who seek perfection in everything are those who cannot attain it in anything</QuoteValue>
</Quote>
<Quote>
<Author>Gustave Flaubert</Author>
<Language>English</Language>
<QuoteValue>Poetry is as precise a thing as geometry</QuoteValue>
</Quote>
<Quote>
<Author>Gustave Flaubert</Author>
<Language>English</Language>
<QuoteValue>Of all lies, art is the least untrue</QuoteValue>
</Quote>
<Quote>
<Author>Gustave Flaubert</Author>
<Language>English</Language>
<QuoteValue>The more humanity advances, the more it is degraded</QuoteValue>
</Quote>
<Quote>
<Author>Guy Fieri</Author>
<Language>English</Language>
<QuoteValue>Short of screaming-hot Thai food, everything can be suitable for kids too</QuoteValue>
</Quote>
<Quote>
<Author>Guy Fieri</Author>
<Language>English</Language>
<QuoteValue>No matter how tough the meat may be, it's going to be tender if you slice it thin enough</QuoteValue>
</Quote>
<Quote>
<Author>Guy Fieri</Author>
<Language>English</Language>
<QuoteValue>You can find tranquility, you can find party, you can find new friends. I'm a cruise convert</QuoteValue>
</Quote>
<Quote>
<Author>Guy Fieri</Author>
<Language>English</Language>
<QuoteValue>There are three people you need in life: an accountant, a fishmonger, and a bail bondsman</QuoteValue>
</Quote>
<Quote>
<Author>Guy Fieri</Author>
<Language>English</Language>
<QuoteValue>If you looked in my fridge, you'd see maybe 12 different mustards</QuoteValue>
</Quote>
<Quote>
<Author>Guy Fieri</Author>
<Language>English</Language>
<QuoteValue>I wake up in the morning thinking about food</QuoteValue>
</Quote>
<Quote>
<Author>Guy Fieri</Author>
<Language>English</Language>
<QuoteValue>Some people are just born to cook and talk</QuoteValue>
</Quote>
<Quote>
<Author>Guy Fieri</Author>
<Language>English</Language>
<QuoteValue>You don't have to eat a whole cheeseburger, just take a piece of the cheeseburger</QuoteValue>
</Quote>
<Quote>
<Author>Guy Fieri</Author>
<Language>English</Language>
<QuoteValue>Losing my sister to cancer was... That was the worst thing in the world, man</QuoteValue>
</Quote>
<Quote>
<Author>Guy Fieri</Author>
<Language>English</Language>
<QuoteValue>In Japanese, sushi does not mean raw fish. It means seasoned rice</QuoteValue>
</Quote>
<Quote>
<Author>Guy Kawasaki</Author>
<Language>English</Language>
<QuoteValue>If you have to put someone on a pedestal, put teachers. They are society's heroes</QuoteValue>
</Quote>
<Quote>
<Author>Guy Kawasaki</Author>
<Language>English</Language>
<QuoteValue>Patience is the art of concealing your impatience</QuoteValue>
</Quote>
<Quote>
<Author>Guy Kawasaki</Author>
<Language>English</Language>
<QuoteValue>Great companies start because the founders want to change the world... not make a fast buck</QuoteValue>
</Quote>
<Quote>
<Author>Guy Kawasaki</Author>
<Language>English</Language>
<QuoteValue>Evangelism is selling a dream</QuoteValue>
</Quote>
<Quote>
<Author>Guy Kawasaki</Author>
<Language>English</Language>
<QuoteValue>A good idea is about ten percent and implementation and hard work, and luck is 90 percent</QuoteValue>
</Quote>
<Quote>
<Author>Guy Kawasaki</Author>
<Language>English</Language>
<QuoteValue>Ambitious failure, magnificent failure, is a very good thing</QuoteValue>
</Quote>
<Quote>
<Author>Guy Kawasaki</Author>
<Language>English</Language>
<QuoteValue>Entrepreneurship is not for everyone</QuoteValue>
</Quote>
<Quote>
<Author>Guy Kawasaki</Author>
<Language>English</Language>
<QuoteValue>Social media allows me to pick my times for social interaction</QuoteValue>
</Quote>
<Quote>
<Author>Guy Kawasaki</Author>
<Language>English</Language>
<QuoteValue>I do have a peripatetic and active intellectual curiosity</QuoteValue>
</Quote>
<Quote>
<Author>Guy Kawasaki</Author>
<Language>English</Language>
<QuoteValue>Entitlement is the opposite of enchantment</QuoteValue>
</Quote>
<Quote>
<Author>Gwen Ifill</Author>
<Language>English</Language>
<QuoteValue>Hope springs eternal, even in politics</QuoteValue>
</Quote>
<Quote>
<Author>Gwen Ifill</Author>
<Language>English</Language>
<QuoteValue>Can't disagree with the need for a grasp of history</QuoteValue>
</Quote>
<Quote>
<Author>Gwen Ifill</Author>
<Language>English</Language>
<QuoteValue>The common agenda both sides seem to share is: Whatever works</QuoteValue>
</Quote>
<Quote>
<Author>Gwen Ifill</Author>
<Language>English</Language>
<QuoteValue>Is it unreasonable to have proof of citizenship when entering another country?</QuoteValue>
</Quote>
<Quote>
<Author>Gwen Ifill</Author>
<Language>English</Language>
<QuoteValue>On immigration, there are a lot of hurdles before anything arrives at the White House</QuoteValue>
</Quote>
<Quote>
<Author>Gwen Ifill</Author>
<Language>English</Language>
<QuoteValue>Did I say that the President's entire job is image management? Of course not</QuoteValue>
</Quote>
<Quote>
<Author>Gwen Ifill</Author>
<Language>English</Language>
<QuoteValue>Tony Blair - good thing there are not parliamentary elections in this country</QuoteValue>
</Quote>
<Quote>
<Author>Gwen Ifill</Author>
<Language>English</Language>
<QuoteValue>I got my first job by exceeding expectations</QuoteValue>
</Quote>
<Quote>
<Author>Gwen Ifill</Author>
<Language>English</Language>
<QuoteValue>Hyperbole is not easily dealt with. Usually, it collapses under its own weight</QuoteValue>
</Quote>
<Quote>
<Author>Gwen Ifill</Author>
<Language>English</Language>
<QuoteValue>My job as a reporter is not to know what I think</QuoteValue>
</Quote>
<Quote>
<Author>Gwen Stefani</Author>
<Language>English</Language>
<QuoteValue>Life is short and you've got to get the most out of it</QuoteValue>
</Quote>
<Quote>
<Author>Gwen Stefani</Author>
<Language>English</Language>
<QuoteValue>At a certain point I'm going to want to have a family</QuoteValue>
</Quote>
<Quote>
<Author>Gwen Stefani</Author>
<Language>English</Language>
<QuoteValue>Writing songs is super intimate. It's a bit like getting naked</QuoteValue>
</Quote>
<Quote>
<Author>Gwen Stefani</Author>
<Language>English</Language>
<QuoteValue>Being in a band you can wear whatever you want - it's like an excuse for Halloween every day</QuoteValue>
</Quote>
<Quote>
<Author>Gwen Stefani</Author>
<Language>English</Language>
<QuoteValue>Everything works out how it should</QuoteValue>
</Quote>
<Quote>
<Author>Gwen Stefani</Author>
<Language>English</Language>
<QuoteValue>I don't have a strong sense of self-worth unless I'm doing something</QuoteValue>
</Quote>
<Quote>
<Author>Gwen Stefani</Author>
<Language>English</Language>
<QuoteValue>I think I've been able to fool a lot of people because I know I'm a dork. I'm a geek</QuoteValue>
</Quote>
<Quote>
<Author>Gwen Stefani</Author>
<Language>English</Language>
<QuoteValue>I'm lucky to not have a real job, to be able to express myself, be creative and be relevant</QuoteValue>
</Quote>
<Quote>
<Author>Gwen Stefani</Author>
<Language>English</Language>
<QuoteValue>I want to be a guy, but I want to wear a lot of makeup</QuoteValue>
</Quote>
<Quote>
<Author>Gwen Stefani</Author>
<Language>English</Language>
<QuoteValue>Sometimes you have to sacrifice your performance for high heels</QuoteValue>
</Quote>
<Quote>
<Author>Gwendoline Christie</Author>
<Language>English</Language>
<QuoteValue>I think everyone loves a slash of red lipstick</QuoteValue>
</Quote>
<Quote>
<Author>Gwendoline Christie</Author>
<Language>English</Language>
<QuoteValue>Rory McCann is an amazing actor and a very strong man</QuoteValue>
</Quote>
<Quote>
<Author>Gwendoline Christie</Author>
<Language>English</Language>
<QuoteValue>I don't know, so much of women's femininity is tied up with their hair</QuoteValue>
</Quote>
<Quote>
<Author>Gwendoline Christie</Author>
<Language>English</Language>
<QuoteValue>My father always said, 'You can do anything a man can do.'</QuoteValue>
</Quote>
<Quote>
<Author>Gwendoline Christie</Author>
<Language>English</Language>
<QuoteValue>I'd love to work with Lena Headey, Alfie Allen, Charles Dance. I'd love to work with Peter Dinklage</QuoteValue>
</Quote>
<Quote>
<Author>Gwendoline Christie</Author>
<Language>English</Language>
<QuoteValue>My pseudonym is 'George R. R. Martin.' That guy's just an actor</QuoteValue>
</Quote>
<Quote>
<Author>Gwendoline Christie</Author>
<Language>English</Language>
<QuoteValue>I describe my personal style as 'mythic space horse with chocolate box tendencies.'</QuoteValue>
</Quote>
<Quote>
<Author>Gwendoline Christie</Author>
<Language>English</Language>
<QuoteValue>If I were amazing with a sword, I wouldn't care about the tender things in life</QuoteValue>
</Quote>
<Quote>
<Author>Gwendoline Christie</Author>
<Language>English</Language>
<QuoteValue>The whole format of 'Game of Thrones' is that you just don't know what to expect</QuoteValue>
</Quote>
<Quote>
<Author>Gwendoline Christie</Author>
<Language>English</Language>
<QuoteValue>People come up to me and say, 'You look so much better in real life.'</QuoteValue>
</Quote>
<Quote>
<Author>Gwyneth Paltrow</Author>
<Language>English</Language>
<QuoteValue>I'm not sure how healthy bacon is in general, but I know it's incredibly delicious</QuoteValue>
</Quote>
<Quote>
<Author>Gwyneth Paltrow</Author>
<Language>English</Language>
<QuoteValue>My father, he was like the rock, the guy you went to with every problem</QuoteValue>
</Quote>
<Quote>
<Author>Gwyneth Paltrow</Author>
<Language>English</Language>
<QuoteValue>I have a very highly developed sense of denial</QuoteValue>
</Quote>
<Quote>
<Author>Gwyneth Paltrow</Author>
<Language>English</Language>
<QuoteValue>Beauty, to me is about being comfortable in your own skin</QuoteValue>
</Quote>
<Quote>
<Author>Gwyneth Paltrow</Author>
<Language>English</Language>
<QuoteValue>The older I get, the more open-minded I get, the less judgmental I get</QuoteValue>
</Quote>
<Quote>
<Author>Gwyneth Paltrow</Author>
<Language>English</Language>
<QuoteValue>The Jewish part of me is superstitious</QuoteValue>
</Quote>
<Quote>
<Author>Gwyneth Paltrow</Author>
<Language>English</Language>
<QuoteValue>Sometimes when things you love get really commercial, you end up feeling betrayed by it</QuoteValue>
</Quote>
<Quote>
<Author>Gwyneth Paltrow</Author>
<Language>English</Language>
<QuoteValue>Because I was newly pregnant, I was sick as a dog, yet I knew all my lines from a year before</QuoteValue>
</Quote>
<Quote>
<Author>Gwyneth Paltrow</Author>
<Language>English</Language>
<QuoteValue>I try to avoid barbecue potato chips. They're my weakness</QuoteValue>
</Quote>
<Quote>
<Author>Gwyneth Paltrow</Author>
<Language>English</Language>
<QuoteValue>When I pass a flowering zucchini plant in a garden, my heart skips a beat</QuoteValue>
</Quote>
<Quote>
<Author>Gyorgy Ligeti</Author>
<Language>English</Language>
<QuoteValue>If you come from Paris to Budapest you think you are in Moscow</QuoteValue>
</Quote>
<Quote>
<Author>Gyorgy Ligeti</Author>
<Language>English</Language>
<QuoteValue>But if you go from Moscow to Budapest you think you are in Paris</QuoteValue>
</Quote>
<Quote>
<Author>Gyorgy Ligeti</Author>
<Language>English</Language>
<QuoteValue>My grandfather was not a musician but he was an artist - a painter, a decorative painter</QuoteValue>
</Quote>
<Quote>
<Author>Gyorgy Ligeti</Author>
<Language>English</Language>
<QuoteValue>I listen to all kinds of music - new music, old music, music of my colleagues, everything</QuoteValue>
</Quote>
<Quote>
<Author>Gyorgy Ligeti</Author>
<Language>English</Language>
<QuoteValue>Stravinsky used Mother Goose. He was influenced by Mother Goose, indirectly, but very beautifully</QuoteValue>
</Quote>
<Quote>
<Author>Gyorgy Ligeti</Author>
<Language>English</Language>
<QuoteValue>But I do not want to use Hungarian verses for British people</QuoteValue>
</Quote>
<Quote>
<Author>Gyorgy Ligeti</Author>
<Language>English</Language>
<QuoteValue>I don't read such boring things. Life is too short</QuoteValue>
</Quote>
<Quote>
<Author>Gyorgy Ligeti</Author>
<Language>English</Language>
<QuoteValue>In January 1944 I was called up by the Forced Labor Service, but I deserted on October 10, 1944</QuoteValue>
</Quote>
<Quote>
<Author>Gyorgy Ligeti</Author>
<Language>English</Language>
<QuoteValue>I lived under the Nazis and under the Communists</QuoteValue>
</Quote>
<Quote>
<Author>Gyorgy Ligeti</Author>
<Language>English</Language>
<QuoteValue>I know already the music I will write. But the words? I have not yet decided</QuoteValue>
</Quote>
<Quote>
<Author>H. Rap Brown</Author>
<Language>English</Language>
<QuoteValue>They cannot divide us by saying that you're middle class or you're lower class</QuoteValue>
</Quote>
<Quote>
<Author>H. Rap Brown</Author>
<Language>English</Language>
<QuoteValue>And understand: class differences will not save you</QuoteValue>
</Quote>
<Quote>
<Author>H. Rap Brown</Author>
<Language>English</Language>
<QuoteValue>I say violence is necessary. It is as American as cherry pie</QuoteValue>
</Quote>
<Quote>
<Author>H. Rap Brown</Author>
<Language>English</Language>
<QuoteValue>Revolution comes when human beings set out to correct decadent institutions</QuoteValue>
</Quote>
<Quote>
<Author>H. Rap Brown</Author>
<Language>English</Language>
<QuoteValue>When you understand your obligations to God then you can understand your obligations to society</QuoteValue>
</Quote>
<Quote>
<Author>H. Rap Brown</Author>
<Language>English</Language>
<QuoteValue>You've got to stop dividing yourselves. You got to organize</QuoteValue>
</Quote>
<Quote>
<Author>H. Rap Brown</Author>
<Language>English</Language>
<QuoteValue>Yes, politics IS war without bloodshed; and war is an extension of those politics</QuoteValue>
</Quote>
<Quote>
<Author>H. Rap Brown</Author>
<Language>English</Language>
<QuoteValue>See, justice is a joke in this country, and it stinks of its hypocricy</QuoteValue>
</Quote>
<Quote>
<Author>H. Rap Brown</Author>
<Language>English</Language>
<QuoteValue>See, it's no in between: you're either free or you're a slave</QuoteValue>
</Quote>
<Quote>
<Author>H. Rap Brown</Author>
<Language>English</Language>
<QuoteValue>One of the lies that we tell ourselves is that we're making progress; but Huey's chair's empty</QuoteValue>
</Quote>
<Quote>
<Author>Haile Gebrselassie</Author>
<Language>English</Language>
<QuoteValue>I haven't done a marathon for a long time. So we'll see. I will need good luck</QuoteValue>
</Quote>
<Quote>
<Author>Haile Gebrselassie</Author>
<Language>English</Language>
<QuoteValue>I have to change a lot of things before I become a good marathon runner</QuoteValue>
</Quote>
<Quote>
<Author>Haile Gebrselassie</Author>
<Language>English</Language>
<QuoteValue>I wanted to experience New York, to look up and see buildings</QuoteValue>
</Quote>
<Quote>
<Author>Haile Gebrselassie</Author>
<Language>English</Language>
<QuoteValue>My father didn't think running was sensible. He told me running is just wasting time</QuoteValue>
</Quote>
<Quote>
<Author>Haile Gebrselassie</Author>
<Language>English</Language>
<QuoteValue>If you're planning only to make money and nothing else, you'll be broke</QuoteValue>
</Quote>
<Quote>
<Author>Haile Gebrselassie</Author>
<Language>English</Language>
<QuoteValue>I'm never satisfied</QuoteValue>
</Quote>
<Quote>
<Author>Haile Gebrselassie</Author>
<Language>English</Language>
<QuoteValue>Once you have commitment, you need the discipline and hard work to get you there</QuoteValue>
</Quote>
<Quote>
<Author>Haile Gebrselassie</Author>
<Language>English</Language>
<QuoteValue>I think if you come first with a new world record, that is the best</QuoteValue>
</Quote>
<Quote>
<Author>Haile Gebrselassie</Author>
<Language>English</Language>
<QuoteValue>I used to run to school, 10k every day. And this at altitude, perfect preparation, really</QuoteValue>
</Quote>
<Quote>
<Author>Haile Gebrselassie</Author>
<Language>English</Language>
<QuoteValue>When you promise something, you must fulfill it</QuoteValue>
</Quote>
<Quote>
<Author>Hailee Steinfeld</Author>
<Language>English</Language>
<QuoteValue>My mom taught me to live by the three p's: to always be passionate, persistent, and prepared</QuoteValue>
</Quote>
<Quote>
<Author>Hailee Steinfeld</Author>
<Language>English</Language>
<QuoteValue>Everything I do now is a first</QuoteValue>
</Quote>
<Quote>
<Author>Hailee Steinfeld</Author>
<Language>English</Language>
<QuoteValue>When I was 13, I looked like I could play 16, and I wasn't mature enough to play 16</QuoteValue>
</Quote>
<Quote>
<Author>Hailee Steinfeld</Author>
<Language>English</Language>
<QuoteValue>It's hard not to love everything Prada does</QuoteValue>
</Quote>
<Quote>
<Author>Hailee Steinfeld</Author>
<Language>English</Language>
<QuoteValue>It needs to be said and heard: it's OK to be who you are</QuoteValue>
</Quote>
<Quote>
<Author>Hailee Steinfeld</Author>
<Language>English</Language>
<QuoteValue>Every girl wishes she was Juliet in some version of their life</QuoteValue>
</Quote>
<Quote>
<Author>Hailee Steinfeld</Author>
<Language>English</Language>
<QuoteValue>The idea of revenge coming from a 14-year-old girl isn't, you know, exactly right</QuoteValue>
</Quote>
<Quote>
<Author>Hailee Steinfeld</Author>
<Language>English</Language>
<QuoteValue>I was just another girl</QuoteValue>
</Quote>
<Quote>
<Author>Hailee Steinfeld</Author>
<Language>English</Language>
<QuoteValue>Facebook is my life</QuoteValue>
</Quote>
<Quote>
<Author>Hailee Steinfeld</Author>
<Language>English</Language>
<QuoteValue>I love the film route and I'm gong to try my hardest to stay on it</QuoteValue>
</Quote>
<Quote>
<Author>Hakeem Olajuwon</Author>
<Language>English</Language>
<QuoteValue>My type of basketball is about how to create space, how to maneuver, how to get your shot off</QuoteValue>
</Quote>
<Quote>
<Author>Hakeem Olajuwon</Author>
<Language>English</Language>
<QuoteValue>God comes first. Paradise is not cheap</QuoteValue>
</Quote>
<Quote>
<Author>Hakeem Olajuwon</Author>
<Language>English</Language>
<QuoteValue>I always keep a ball in the car. You never know</QuoteValue>
</Quote>
<Quote>
<Author>Hakeem Olajuwon</Author>
<Language>English</Language>
<QuoteValue>I remember at the 1996 Olympics in Atlanta, Shaq always wanted me to show him steps over and over</QuoteValue>
</Quote>
<Quote>
<Author>Hakeem Olajuwon</Author>
<Language>English</Language>
<QuoteValue>My background playing soccer gave me a natural advantage over many of the American-born players</QuoteValue>
</Quote>
<Quote>
<Author>Hakeem Olajuwon</Author>
<Language>English</Language>
<QuoteValue>Basketball is in my blood. It is my obligation to try</QuoteValue>
</Quote>
<Quote>
<Author>Hakeem Olajuwon</Author>
<Language>English</Language>
<QuoteValue>I'm the kind of person who always wants more</QuoteValue>
</Quote>
<Quote>
<Author>Hakeem Olajuwon</Author>
<Language>English</Language>
<QuoteValue>The key to fashion is, you don't want to look like you're trying. You've gotta be natural</QuoteValue>
</Quote>
<Quote>
<Author>Hakeem Olajuwon</Author>
<Language>English</Language>
<QuoteValue>I've now been in this country for thirteen years, since I was seventeen. So this is my second home</QuoteValue>
</Quote>
<Quote>
<Author>Hakeem Olajuwon</Author>
<Language>English</Language>
<QuoteValue>I'm shy, but sometimes my voice is so clear and strong</QuoteValue>
</Quote>
<Quote>
<Author>Hal Sparks</Author>
<Language>English</Language>
<QuoteValue>It's better to waste money, than it is to waste time. You can always get more money</QuoteValue>
</Quote>
<Quote>
<Author>Hal Sparks</Author>
<Language>English</Language>
<QuoteValue>Sometimes I play guitar like a frustrated drummer</QuoteValue>
</Quote>
<Quote>
<Author>Hal Sparks</Author>
<Language>English</Language>
<QuoteValue>Jerry Springer' is just kind of the chubby, redneck version of throwing Christians to the lions</QuoteValue>
</Quote>
<Quote>
<Author>Hal Sparks</Author>
<Language>English</Language>
<QuoteValue>I try to be as ignorant about things as I can</QuoteValue>
</Quote>
<Quote>
<Author>Hal Sparks</Author>
<Language>English</Language>
<QuoteValue>Anyone who still supports George Bush would still let Michael Jackson babysit their kids</QuoteValue>
</Quote>
<Quote>
<Author>Hal Sparks</Author>
<Language>English</Language>
<QuoteValue>If I have anything, it's tenacity</QuoteValue>
</Quote>
<Quote>
<Author>Hal Sparks</Author>
<Language>English</Language>
<QuoteValue>Political and social change is always a stagger-step process</QuoteValue>
</Quote>
<Quote>
<Author>Hal Sparks</Author>
<Language>English</Language>
<QuoteValue>Truth be told, ginormous portions have become a pet peeve of mine</QuoteValue>
</Quote>
<Quote>
<Author>Hal Sparks</Author>
<Language>English</Language>
<QuoteValue>It's better to waste money than time. You can always get more money</QuoteValue>
</Quote>
<Quote>
<Author>Hal Sparks</Author>
<Language>English</Language>
<QuoteValue>I've been doing stand-up since I was 15 years old</QuoteValue>
</Quote>
<Quote>
<Author>Halle Berry</Author>
<Language>English</Language>
<QuoteValue>I spent a lot of time with a crown on my head</QuoteValue>
</Quote>
<Quote>
<Author>Halle Berry</Author>
<Language>English</Language>
<QuoteValue>My whole life I've had the fear that I was going to be abandoned</QuoteValue>
</Quote>
<Quote>
<Author>Halle Berry</Author>
<Language>English</Language>
<QuoteValue>I think it's always best to be who you are</QuoteValue>
</Quote>
<Quote>
<Author>Halle Berry</Author>
<Language>English</Language>
<QuoteValue>I carried my Oscar to bed with me. My first and only three-way happened that night</QuoteValue>
</Quote>
<Quote>
<Author>Halle Berry</Author>
<Language>English</Language>
<QuoteValue>I like Doritos. I'm usually watching 'The Biggest Loser' eating Doritos</QuoteValue>
</Quote>
<Quote>
<Author>Halle Berry</Author>
<Language>English</Language>
<QuoteValue>I'm just going to live my life and be who I am</QuoteValue>
</Quote>
<Quote>
<Author>Halle Berry</Author>
<Language>English</Language>
<QuoteValue>A person's self-esteem has nothing to do with how she looks</QuoteValue>
</Quote>
</Quotes>

